numcodecs_wasm_zfp/__init__.py
numcodecs_wasm_zfp/__init__.pyi
numcodecs_wasm_zfp/codec.wasm
numcodecs_wasm_zfp/py.typed
numcodecs_wasm_zfp-0.6.0.dist-info/METADATA
numcodecs_wasm_zfp-0.6.0.dist-info/WHEEL
numcodecs_wasm_zfp-0.6.0.dist-info/entry_points.txt
numcodecs_wasm_zfp-0.6.0.dist-info/top_level.txt
numcodecs_wasm_zfp-0.6.0.dist-info/RECORD
