Metadata-Version: 2.4
Name: numcodecs_wasm_zfp
Version: 0.6.0
Summary: numcodecs-zfp compression codec compiled to WebAssembly
Author-email: Juniper Tyree <juniper.tyree@helsinki.fi>
Maintainer-email: Juniper Tyree <juniper.tyree@helsinki.fi>
License: Copyright (c) 2024-2025, Juniper Tyree
Requires-Python: >=3.10
Requires-Dist: numcodecs-wasm~=0.2.0
